MANIFEST.in
README.rst
setup.py
collective/.DS_Store
collective/__init__.py
collective/__init__.pyc
collective.ptg.quicksand.egg-info/PKG-INFO
collective.ptg.quicksand.egg-info/SOURCES.txt
collective.ptg.quicksand.egg-info/dependency_links.txt
collective.ptg.quicksand.egg-info/entry_points.txt
collective.ptg.quicksand.egg-info/namespace_packages.txt
collective.ptg.quicksand.egg-info/not-zip-safe
collective.ptg.quicksand.egg-info/requires.txt
collective.ptg.quicksand.egg-info/top_level.txt
collective/ptg/.DS_Store
collective/ptg/__init__.py
collective/ptg/__init__.pyc
collective/ptg/quicksand/.DS_Store
collective/ptg/quicksand/__init__.py
collective/ptg/quicksand/__init__.pyc
collective/ptg/quicksand/configure.zcml
collective/ptg/quicksand/i18n.sh
collective/ptg/quicksand/quicksand.pt
collective/ptg/quicksand/locales/.DS_Store
collective/ptg/quicksand/locales/collective.ptg.quicksand.pot
collective/ptg/quicksand/locales/en/LC_MESSAGES/collective.ptg.quicksand.po
collective/ptg/quicksand/locales/no/.DS_Store
collective/ptg/quicksand/locales/no/LC_MESSAGES/collective.ptg.quicksand.po
collective/ptg/quicksand/resources/.DS_Store
collective/ptg/quicksand/resources/boxstyle.css
collective/ptg/quicksand/resources/iconstyle.css
collective/ptg/quicksand/resources/jquery.easing.1.3.js
collective/ptg/quicksand/resources/jquery.quicksand.js
collective/ptg/quicksand/resources/no_style.css
collective/ptg/quicksand/resources/style.css
docs/HISTORY.txt
docs/INSTALL.txt
docs/LICENSE.GPL
docs/LICENSE.txt