Metadata-Version: 1.0
Name: collective.ptg.quicksand
Version: 0.3
Summary: Sheet gallery for plonetruegallery
Home-page: https://github.com/collective/collective.ptg.quicksand
Author: Espen Moe-Nilssen
Author-email: espen@medialog.no
License: GPL
Keywords: plonetruegallery gallery plone addon
Platform: UNKNOWN
Classifier: Framework :: Plone
Classifier: Programming Language :: Python
